python_bluesky_taskgraph/__init__.py
python_bluesky_taskgraph/__main__.py
python_bluesky_taskgraph/_version_git.py
python_bluesky_taskgraph/core/__init__.py
python_bluesky_taskgraph/core/decision_engine.py
python_bluesky_taskgraph/core/task.py
python_bluesky_taskgraph/core/task_graph.py
python_bluesky_taskgraph/core/types.py
python_bluesky_taskgraph/tasks/__init__.py
python_bluesky_taskgraph/tasks/behavioural_tasks.py
python_bluesky_taskgraph/tasks/functional_tasks.py
python_bluesky_taskgraph/tasks/stub_tasks.py
python_bluesky_taskgraph-0.1.dist-info/LICENSE
python_bluesky_taskgraph-0.1.dist-info/METADATA
python_bluesky_taskgraph-0.1.dist-info/WHEEL
python_bluesky_taskgraph-0.1.dist-info/entry_points.txt
python_bluesky_taskgraph-0.1.dist-info/top_level.txt
python_bluesky_taskgraph-0.1.dist-info/RECORD
