Metadata-Version: 2.1
Name: python-bluesky-taskgraph
Version: 0.1
Summary: A Library to add TaskGraph implementation of plans to Bluesky
Home-page: https://github.com/DiamondLightSource/python-bluesky-taskgraph
Author: Joseph Ware
Author-email: joseph.ware@diamond.ac.uk
License: Apache License 2.0
Platform: UNKNOWN
Classifier: Development Status :: 4 - Beta
Classifier: License :: OSI Approved :: Apache Software License
Classifier: Programming Language :: Python :: 3.8
Classifier: Programming Language :: Python :: 3.9
Requires-Python: >=3.8
Requires-Dist: bluesky
Requires-Dist: ophyd
Requires-Dist: typing
Provides-Extra: dev
Requires-Dist: black (==21.9b0) ; extra == 'dev'
Requires-Dist: isort (>5.0) ; extra == 'dev'
Requires-Dist: pytest-cov ; extra == 'dev'
Requires-Dist: mypy ; extra == 'dev'
Requires-Dist: flake8-isort ; extra == 'dev'
Requires-Dist: sphinx-rtd-theme-github-versions ; extra == 'dev'
Requires-Dist: pre-commit ; extra == 'dev'
